simplesumproduct/__init__.py
simplesumproduct/producttool.py
simplesumproduct/sumtool.py
simplesumproduct-0.0.2.dist-info/LICENSE
simplesumproduct-0.0.2.dist-info/METADATA
simplesumproduct-0.0.2.dist-info/WHEEL
simplesumproduct-0.0.2.dist-info/top_level.txt
simplesumproduct-0.0.2.dist-info/RECORD
